goldenhinges/OverhangSetOptimizer.py
goldenhinges/OverhangsSelector.py
goldenhinges/__init__.py
goldenhinges/biotools.py
goldenhinges/clique_methods.py
goldenhinges/reports.py
goldenhinges/version.py
goldenhinges-0.2.3.dist-info/LICENCE.txt
goldenhinges-0.2.3.dist-info/METADATA
goldenhinges-0.2.3.dist-info/WHEEL
goldenhinges-0.2.3.dist-info/top_level.txt
goldenhinges-0.2.3.dist-info/RECORD
