Metadata-Version: 2.1
Name: goldenhinges
Version: 0.2.3
Summary: DNA overhang design for Golden Gate etc.
Home-page: https://github.com/Edinburgh-Genome-Foundry/GoldenHinges
Author: Zulko
License: MIT
Keywords: DNA assembly overhangs constraint-programming synthetic-biology
Platform: UNKNOWN
License-File: LICENCE.txt
Requires-Dist: numpy
Requires-Dist: Numberjack
Requires-Dist: Biopython
Requires-Dist: networkx
Requires-Dist: proglog
Requires-Dist: dna-features-viewer
Requires-Dist: tqdm
Requires-Dist: dnachisel
Requires-Dist: geneblocks
